[{"id":3207,"season":1901,"week":1,"seasonType":"postseason","startDate":"1902-01-01T00:00:00.000Z","startTimeTBD":null,"completed":true,"neutralSite":true,"conferenceGame":null,"attendance":null,"venueId":null,"venue":null,"homeId":130,"homeTeam":"Michigan","homeConference":"Western","homeClassification":"fbs","homePoints":49,"homeLineScores":[],"hohomePostgameWinProbability":null,"homePregameElo":2392,"homePostgameElo":2432,"awayId":24,"awayTeam":"Stanford","awayConference":null,"awayClassification":null,"awayPoints":0,"awayLineScores":[],"awayPostgameWinProbability":null,"awayPregameElo":1500,"awayPostgameElo":1460,"excitementIndex":null,"highlights":null,"notes":null}]