[{"id":16251,"season":1928,"week":1,"season_type":"postseason","start_date":"1929-01-01T00:00:00.000Z","start_time_tbd":null,"completed":true,"neutral_site":true,"conference_game":null,"attendance":null,"venue_id":null,"venue":null,"home_id":59,"home_team":"Georgia Tech","home_conference":"Southern","home_division":"fbs","home_points":8,"home_line_scores":[],"home_post_win_prob":null,"home_pregame_elo":1887,"home_postgame_elo":1886,"away_id":25,"away_team":"California","away_conference":"Pacific","away_division":"fbs","away_points":7,"away_line_scores":[],"away_post_win_prob":null,"away_pregame_elo":1775,"away_postgame_elo":1776,"excitement_index":null,"highlights":null,"notes":null}]