[{"id":20134,"season":1934,"week":1,"seasonType":"postseason","startDate":"1935-01-01T00:00:00.000Z","startTimeTBD":null,"completed":true,"neutralSite":true,"conferenceGame":null,"attendance":null,"venueId":null,"venue":null,"homeId":2655,"homeTeam":"Tulane","homeConference":"SEC","homeClassification":"fbs","homePoints":20,"homeLineScores":[],"hohomePostgameWinProbability":null,"homePregameElo":1749,"homePostgameElo":1765,"awayId":218,"awayTeam":"Temple","awayConference":"FBS Independents","awayClassification":"fbs","awayPoints":14,"awayLineScores":[],"awayPostgameWinProbability":null,"awayPregameElo":1787,"awayPostgameElo":1771,"excitementIndex":null,"highlights":null,"notes":null},{"id":20132,"season":1934,"week":1,"seasonType":"postseason","startDate":"1935-01-01T00:00:00.000Z","startTimeTBD":null,"completed":true,"neutralSite":true,"conferenceGame":null,"attendance":null,"venueId":null,"venue":null,"homeId":2390,"homeTeam":"Miami","homeConference":null,"homeClassification":null,"homePoints":0,"homeLineScores":[],"hohomePostgameWinProbability":null,"homePregameElo":1441,"homePostgameElo":1400,"awayId":2083,"awayTeam":"Bucknell","awayConference":"FBS Independents","awayClassification":"fbs","awayPoints":26,"awayLineScores":[],"awayPostgameWinProbability":null,"awayPregameElo":1623,"awayPostgameElo":1664,"excitementIndex":null,"highlights":null,"notes":null},{"id":20131,"season":1934,"week":1,"seasonType":"postseason","startDate":"1935-01-01T00:00:00.000Z","startTimeTBD":null,"completed":true,"neutralSite":true,"conferenceGame":null,"attendance":null,"venueId":null,"venue":null,"homeId":333,"homeTeam":"Alabama","homeConference":"SEC","homeClassification":"fbs","homePoints":29,"homeLineScores":[],"hohomePostgameWinProbability":null,"homePregameElo":2032,"homePostgameElo":2060,"awayId":24,"awayTeam":"Stanford","awayConference":"Pacific","awayClassification":"fbs","awayPoints":13,"awayLineScores":[],"awayPostgameWinProbability":null,"awayPregameElo":1891,"awayPostgameElo":1863,"excitementIndex":null,"highlights":null,"notes":null}]