[{"id":43260,"season":1971,"week":1,"seasonType":"postseason","startDate":"1971-12-18T00:00:00.000Z","startTimeTBD":null,"completed":true,"neutralSite":true,"conferenceGame":null,"attendance":null,"venueId":null,"venue":null,"homeId":235,"homeTeam":"Memphis","homeConference":"Missouri Valley","homeClassification":"fbs","homePoints":28,"homeLineScores":[],"hohomePostgameWinProbability":null,"homePregameElo":1635,"homePostgameElo":1680,"awayId":23,"awayTeam":"San José State","awayConference":"PCAA","awayClassification":"fbs","awayPoints":9,"awayLineScores":[],"awayPostgameWinProbability":null,"awayPregameElo":1576,"awayPostgameElo":1531,"excitementIndex":null,"highlights":null,"notes":null},{"id":43259,"season":1971,"week":1,"seasonType":"postseason","startDate":"1971-12-18T00:00:00.000Z","startTimeTBD":null,"completed":true,"neutralSite":true,"conferenceGame":null,"attendance":null,"venueId":null,"venue":null,"homeId":99,"homeTeam":"LSU","homeConference":"SEC","homeClassification":"fbs","homePoints":33,"homeLineScores":[],"hohomePostgameWinProbability":null,"homePregameElo":2005,"homePostgameElo":2030,"awayId":66,"awayTeam":"Iowa State","awayConference":"Big 8","awayClassification":"fbs","awayPoints":15,"awayLineScores":[],"awayPostgameWinProbability":null,"awayPregameElo":1773,"awayPostgameElo":1748,"excitementIndex":null,"highlights":null,"notes":null},{"id":43261,"season":1971,"week":1,"seasonType":"postseason","startDate":"1971-12-20T00:00:00.000Z","startTimeTBD":null,"completed":true,"neutralSite":true,"conferenceGame":null,"attendance":null,"venueId":null,"venue":null,"homeId":2633,"homeTeam":"Tennessee","homeConference":"SEC","homeClassification":"fbs","homePoints":14,"homeLineScores":[],"hohomePostgameWinProbability":null,"homePregameElo":1950,"homePostgameElo":1950,"awayId":8,"awayTeam":"Arkansas","awayConference":"Southwest","awayClassification":"fbs","awayPoints":13,"awayLineScores":[],"awayPostgameWinProbability":null,"awayPregameElo":1871,"awayPostgameElo":1871,"excitementIndex":null,"highlights":null,"notes":null},{"id":43262,"season":1971,"week":1,"seasonType":"postseason","startDate":"1971-12-27T00:00:00.000Z","startTimeTBD":null,"completed":true,"neutralSite":true,"conferenceGame":null,"attendance":null,"venueId":null,"venue":null,"homeId":9,"homeTeam":"Arizona State","homeConference":"Western Athletic","homeClassification":"fbs","homePoints":45,"homeLineScores":[],"hohomePostgameWinProbability":null,"homePregameElo":2067,"homePostgameElo":2064,"awayId":52,"awayTeam":"Florida State","awayConference":"FBS Independents","awayClassification":"fbs","awayPoints":38,"awayLineScores":[],"awayPostgameWinProbability":null,"awayPregameElo":1778,"awayPostgameElo":1781,"excitementIndex":null,"highlights":null,"notes":null},{"id":43263,"season":1971,"week":1,"seasonType":"postseason","startDate":"1971-12-28T00:00:00.000Z","startTimeTBD":null,"completed":true,"neutralSite":true,"conferenceGame":null,"attendance":null,"venueId":null,"venue":null,"homeId":2649,"homeTeam":"Toledo","homeConference":"Mid-American","homeClassification":"fbs","homePoints":28,"homeLineScores":[],"hohomePostgameWinProbability":null,"homePregameElo":2003,"homePostgameElo":2008,"awayId":257,"awayTeam":"Richmond","awayConference":"Southern","awayClassification":"fbs","awayPoints":3,"awayLineScores":[],"awayPostgameWinProbability":null,"awayPregameElo":1375,"awayPostgameElo":1370,"excitementIndex":null,"highlights":null,"notes":null},{"id":43264,"season":1971,"week":1,"seasonType":"postseason","startDate":"1971-12-30T00:00:00.000Z","startTimeTBD":null,"completed":true,"neutralSite":true,"conferenceGame":null,"attendance":null,"venueId":null,"venue":null,"homeId":59,"homeTeam":"Georgia Tech","homeConference":"FBS Independents","homeClassification":"fbs","homePoints":18,"homeLineScores":[],"hohomePostgameWinProbability":null,"homePregameElo":1643,"homePostgameElo":1608,"awayId":145,"awayTeam":"Ole Miss","awayConference":"SEC","awayClassification":"fbs","awayPoints":41,"awayLineScores":[],"awayPostgameWinProbability":null,"awayPregameElo":1802,"awayPostgameElo":1837,"excitementIndex":null,"highlights":null,"notes":null},{"id":43266,"season":1971,"week":1,"seasonType":"postseason","startDate":"1971-12-31T00:00:00.000Z","startTimeTBD":null,"completed":true,"neutralSite":true,"conferenceGame":null,"attendance":null,"venueId":null,"venue":null,"homeId":61,"homeTeam":"Georgia","homeConference":"SEC","homeClassification":"fbs","homePoints":7,"homeLineScores":[],"hohomePostgameWinProbability":null,"homePregameElo":1943,"homePostgameElo":1942,"awayId":153,"awayTeam":"North Carolina","awayConference":"ACC","awayClassification":"fbs","awayPoints":3,"awayLineScores":[],"awayPostgameWinProbability":null,"awayPregameElo":1755,"awayPostgameElo":1756,"excitementIndex":null,"highlights":null,"notes":null},{"id":43265,"season":1971,"week":1,"seasonType":"postseason","startDate":"1971-12-31T00:00:00.000Z","startTimeTBD":null,"completed":true,"neutralSite":true,"conferenceGame":null,"attendance":null,"venueId":null,"venue":null,"homeId":248,"homeTeam":"Houston","homeConference":"FBS Independents","homeClassification":"fbs","homePoints":17,"homeLineScores":[],"hohomePostgameWinProbability":null,"homePregameElo":1928,"homePostgameElo":1906,"awayId":38,"awayTeam":"Colorado","awayConference":"Big 8","awayClassification":"fbs","awayPoints":29,"awayLineScores":[],"awayPostgameWinProbability":null,"awayPregameElo":1895,"awayPostgameElo":1917,"excitementIndex":null,"highlights":null,"notes":null},{"id":43270,"season":1971,"week":1,"seasonType":"postseason","startDate":"1972-01-01T00:00:00.000Z","startTimeTBD":null,"completed":true,"neutralSite":true,"conferenceGame":null,"attendance":null,"venueId":null,"venue":null,"homeId":24,"homeTeam":"Stanford","homeConference":"Pac-8","homeClassification":"fbs","homePoints":13,"homeLineScores":[],"hohomePostgameWinProbability":null,"homePregameElo":1803,"homePostgameElo":1812,"awayId":130,"awayTeam":"Michigan","awayConference":"Big Ten","awayClassification":"fbs","awayPoints":12,"awayLineScores":[],"awayPostgameWinProbability":null,"awayPregameElo":2098,"awayPostgameElo":2089,"excitementIndex":null,"highlights":null,"notes":null},{"id":43268,"season":1971,"week":1,"seasonType":"postseason","startDate":"1972-01-01T00:00:00.000Z","startTimeTBD":null,"completed":true,"neutralSite":true,"conferenceGame":null,"attendance":null,"venueId":null,"venue":null,"homeId":201,"homeTeam":"Oklahoma","homeConference":"Big 8","homeClassification":"fbs","homePoints":40,"homeLineScores":[],"hohomePostgameWinProbability":null,"homePregameElo":2115,"homePostgameElo":2146,"awayId":2,"awayTeam":"Auburn","awayConference":"SEC","awayClassification":"fbs","awayPoints":22,"awayLineScores":[],"awayPostgameWinProbability":null,"awayPregameElo":1942,"awayPostgameElo":1911,"excitementIndex":null,"highlights":null,"notes":null},{"id":43267,"season":1971,"week":1,"seasonType":"postseason","startDate":"1972-01-01T00:00:00.000Z","startTimeTBD":null,"completed":true,"neutralSite":true,"conferenceGame":null,"attendance":null,"venueId":null,"venue":null,"homeId":158,"homeTeam":"Nebraska","homeConference":"Big 8","homeClassification":"fbs","homePoints":38,"homeLineScores":[],"hohomePostgameWinProbability":null,"homePregameElo":2223,"homePostgameElo":2305,"awayId":333,"awayTeam":"Alabama","awayConference":"SEC","awayClassification":"fbs","awayPoints":6,"awayLineScores":[],"awayPostgameWinProbability":null,"awayPregameElo":2116,"awayPostgameElo":2034,"excitementIndex":null,"highlights":null,"notes":null},{"id":43269,"season":1971,"week":1,"seasonType":"postseason","startDate":"1972-01-01T00:00:00.000Z","startTimeTBD":null,"completed":true,"neutralSite":true,"conferenceGame":null,"attendance":null,"venueId":null,"venue":null,"homeId":213,"homeTeam":"Penn State","homeConference":"FBS Independents","homeClassification":"fbs","homePoints":30,"homeLineScores":[],"hohomePostgameWinProbability":null,"homePregameElo":2030,"homePostgameElo":2083,"awayId":251,"awayTeam":"Texas","awayConference":"Southwest","awayClassification":"fbs","awayPoints":6,"awayLineScores":[],"awayPostgameWinProbability":null,"awayPregameElo":1899,"awayPostgameElo":1846,"excitementIndex":null,"highlights":null,"notes":null}]